MisTIC/__init__.py
MisTIC/__main__.py
MisTIC/__version__.py
MisTIC/data_loader.py
MisTIC/generate_tx_feature.py
MisTIC/mistic_class.py
MisTIC/plot_fun.py
MisTIC/utility.py
txmistic-0.0.2.dist-info/licenses/LICENSE
txmistic-0.0.2.dist-info/METADATA
txmistic-0.0.2.dist-info/WHEEL
txmistic-0.0.2.dist-info/top_level.txt
txmistic-0.0.2.dist-info/RECORD
