Metadata-Version: 2.4
Name: txMisTIC
Version: 0.0.2
Summary: A probabilistic model for correcting mis-assigned transcripts due to cell segmentation error in imaging-based spatial transcriptomics.
Author: Yuqiu Yang, Erica DePasquale, David Adeleke, Xiangfei Xie, Yunguan Wang
Author-email: Yuqiu.Yang@utsouthwestern.edu, erica.depasquale@cchmc.org, david.adeleke@cchmc.org, xiangfei.xie@cchmc.org, yunguan.wang@cchmc.org
Classifier: Programming Language :: Python :: 3 :: Only
Classifier: Natural Language :: English
Classifier: Intended Audience :: Science/Research
Requires-Python: >=3.9,<3.11
License-File: LICENSE
Requires-Dist: torch==1.13
Requires-Dist: shapely==2.0
Requires-Dist: geopandas==1.0
Requires-Dist: pydeseq2<0.5,>=0.4.6
Requires-Dist: scanpy==1.10
Requires-Dist: numpy<2.0,>=1.24
Requires-Dist: anndata<0.11,>=0.10
Requires-Dist: pyarrow==16.1
Requires-Dist: polars==1.21
Requires-Dist: jupyter
Requires-Dist: ipywidgets
Dynamic: author
Dynamic: author-email
Dynamic: classifier
Dynamic: description
Dynamic: description-content-type
Dynamic: license-file
Dynamic: requires-dist
Dynamic: requires-python
Dynamic: summary
